verysimplemodule/__init__.py
verysimplemodule/add.py
verysimplemodule/subtract.py
verysimplemodule/extras/__init__.py
verysimplemodule/extras/divide.py
verysimplemodule/extras/multiply.py
elihoole_simplemath-0.0.1.dist-info/METADATA
elihoole_simplemath-0.0.1.dist-info/WHEEL
elihoole_simplemath-0.0.1.dist-info/top_level.txt
elihoole_simplemath-0.0.1.dist-info/RECORD
