Metadata-Version: 2.1
Name: elihoole-simplemath
Version: 0.0.1
Summary: A simple package to do simple math operations
Author: Elijah Hoole
Author-email: elijah@senzmate.com
Keywords: python,math,simple,addition,subtraction,multiplication,division
Classifier: Development Status :: 1 - Planning
Classifier: Intended Audience :: Developers
Classifier: Programming Language :: Python :: 3
Classifier: Operating System :: Unix
Classifier: Operating System :: MacOS :: MacOS X
Classifier: Operating System :: Microsoft :: Windows
